kwalitee/worker.py
kwalitee/version.py
kwalitee/tasks.py
kwalitee/config.py
kwalitee/models.py
kwalitee/hooks.py
kwalitee/kwalitee.py
kwalitee/__init__.py
kwalitee/views.py
kwalitee/factory.py
kwalitee/wsgi.py
kwalitee/static/css/jumbotron-narrow.css
kwalitee/static/css/bootstrap.min.css
kwalitee/static/ico/favicon.ico
kwalitee/cli/prepare.py
kwalitee/cli/account.py
kwalitee/cli/check.py
kwalitee/cli/githooks.py
kwalitee/cli/__init__.py
kwalitee/cli/repository.py
kwalitee/templates/account.html
kwalitee/templates/page.html
kwalitee/templates/index.html
kwalitee/templates/branches.html
kwalitee/templates/commit.html
kwalitee/templates/branch.html
kwalitee/templates/repository.html
kwalitee/templates/helpers.html
kwalitee/templates/status.html
kwalitee-0.2.0rc7.dist-info/RECORD
kwalitee-0.2.0rc7.dist-info/WHEEL
kwalitee-0.2.0rc7.dist-info/entry_points.txt
kwalitee-0.2.0rc7.dist-info/DESCRIPTION.rst
kwalitee-0.2.0rc7.dist-info/metadata.json
kwalitee-0.2.0rc7.dist-info/top_level.txt
kwalitee-0.2.0rc7.dist-info/METADATA
