Metadata-Version: 2.0
Name: kwalitee
Version: 0.2.0rc7
Summary: Kwalitee is a tool that runs static analysis checks on Git repository.
Home-page: https://github.com/inveniosoftware/kwalitee
Author: Invenio collaboration
Author-email: info@invenio-software.org
License: GPLv2
Platform: any
Classifier: Development Status :: 5 - Production/Stable
Classifier: Environment :: Web Environment
Classifier: Intended Audience :: Developers
Classifier: License :: OSI Approved :: GNU General Public License v2 (GPLv2)
Classifier: Operating System :: OS Independent
Classifier: Programming Language :: Python :: 2
Classifier: Programming Language :: Python :: 2.7
Classifier: Programming Language :: Python :: 3
Classifier: Programming Language :: Python :: 3.3
Classifier: Programming Language :: Python :: 3.4
Classifier: Programming Language :: Python
Classifier: Topic :: Internet :: WWW/HTTP :: Dynamic Content
Classifier: Topic :: Software Development :: Libraries :: Python Modules
Requires-Dist: alembic
Requires-Dist: colorama
Requires-Dist: Flask
Requires-Dist: Flask-Script
Requires-Dist: Flask-SQLAlchemy
Requires-Dist: pep8
Requires-Dist: pep8-naming
Requires-Dist: pep257 (>=0.5.0)
Requires-Dist: pyflakes
Requires-Dist: flake8-import-order
Requires-Dist: flake8-blind-except
Requires-Dist: pytest
Requires-Dist: requests
Requires-Dist: rq (>=0.4.6)
Requires-Dist: PyYAML
Requires-Dist: GitPython (>=0.3.2.RC1)
